b2g/__init__.py
b2g/clustering.py
b2g/config.py
b2g/grouping.py
b2g/prior_selection.py
b2g/utils.py
b2g/visualization.py
b2g_tools-0.1.3.dist-info/licenses/LICENSE
b2g_tools-0.1.3.dist-info/METADATA
b2g_tools-0.1.3.dist-info/WHEEL
b2g_tools-0.1.3.dist-info/top_level.txt
b2g_tools-0.1.3.dist-info/RECORD
