Metadata-Version: 2.4
Name: b2g_tools
Version: 0.1.3
Summary: Adaptive batch grouping for single-cell RNA-seq data
Home-page: https://github.com/lyotvincent/b2g
Author: B2G Development Team
License: MIT
Project-URL: Homepage, https://github.com/lyotvincent/b2g
Project-URL: Bug Reports, https://github.com/lyotvincent/b2g/issues
Project-URL: Source, https://github.com/lyotvincent/b2g
Keywords: single-cell,bioinformatics,batch-correction,clustering
Classifier: Development Status :: 4 - Beta
Classifier: Intended Audience :: Science/Research
Classifier: Topic :: Scientific/Engineering :: Bio-Informatics
Classifier: License :: OSI Approved :: GNU General Public License v3 (GPLv3)
Classifier: Programming Language :: Python :: 3
Classifier: Programming Language :: Python :: 3.8
Classifier: Programming Language :: Python :: 3.9
Classifier: Programming Language :: Python :: 3.10
Classifier: Programming Language :: Python :: 3.11
Requires-Python: >=3.8
License-File: LICENSE
Requires-Dist: numpy>=1.20.0
Requires-Dist: pandas>=1.3.0
Requires-Dist: scipy>=1.7.0
Requires-Dist: scikit-learn>=1.0.0
Requires-Dist: scikit-bio>=0.5.6
Requires-Dist: scanpy>=1.9.0
Requires-Dist: anndata>=0.8.0
Requires-Dist: matplotlib>=3.4.0
Requires-Dist: metacells>=0.9.0
Requires-Dist: dynamicTreeCut>=0.1.1
Requires-Dist: leidenalg>=0.8.0
Dynamic: author
Dynamic: home-page
Dynamic: license-file
Dynamic: requires-python
